README.md
setup.cfg
setup.py
azurepipelines_optimizely_sdk/__init__.py
azurepipelines_optimizely_sdk/optimizely_config_manager.py
azurepipelines_optimizely_sdk.egg-info/PKG-INFO
azurepipelines_optimizely_sdk.egg-info/SOURCES.txt
azurepipelines_optimizely_sdk.egg-info/dependency_links.txt
azurepipelines_optimizely_sdk.egg-info/not-zip-safe
azurepipelines_optimizely_sdk.egg-info/requires.txt
azurepipelines_optimizely_sdk.egg-info/top_level.txt