Metadata-Version: 1.0
Name: azurepipelines-optimizely-sdk
Version: 0.2
Summary: SDK for optimizely integration
Home-page: http://github.com/microsoft/azurepipelines-optimizely-sdk
Author: Ajay Yadav
Author-email: ajya@microsoft.com
License: MIT
Platform: UNKNOWN
